kacors485/kacors485.py
kacors485/__init__.py
kacors485-1.0.2.dist-info/METADATA
kacors485-1.0.2.dist-info/WHEEL
kacors485-1.0.2.dist-info/top_level.txt
kacors485-1.0.2.dist-info/DESCRIPTION.rst
kacors485-1.0.2.dist-info/metadata.json
kacors485-1.0.2.dist-info/RECORD
