Metadata-Version: 2.0
Name: kacors485
Version: 1.0.2
Summary: Python library to retrive and parse information from kaco inverters over serial interface
Home-page: https://github.com/plieningerweb/kacors485
Author: Andreas Plieninger
Author-email: info@andreasplieninger.com
License: GNU GPLv3
Platform: UNKNOWN
Classifier: License :: OSI Approved :: GNU General Public License (GPL)
Classifier: Intended Audience :: Developers
Classifier: Operating System :: OS Independent
Classifier: Programming Language :: Python :: 2.6
Classifier: Programming Language :: Python :: 2.7
Classifier: Topic :: Software Development :: Libraries
Requires-Dist: pyserial
